LICENSE
MANIFEST.in
README.md
setup.cfg
setup.py
chain3/__init__.py
chain3/admin.py
chain3/contract.py
chain3/exceptions.py
chain3/iban.py
chain3/main.py
chain3/manager.py
chain3/mc.py
chain3/miner.py
chain3/module.py
chain3/net.py
chain3/parity.py
chain3/personal.py
chain3/shh.py
chain3/testing.py
chain3/txpool.py
chain3/version.py
chain3.egg-info/PKG-INFO
chain3.egg-info/SOURCES.txt
chain3.egg-info/dependency_links.txt
chain3.egg-info/not-zip-safe
chain3.egg-info/requires.txt
chain3.egg-info/top_level.txt
chain3/auto/__init__.py
chain3/auto/http.py
chain3/auto/ipc.py
chain3/auto/websocket.py
chain3/gas_strategies/__init__.py
chain3/gas_strategies/rpc.py
chain3/gas_strategies/time_based.py
chain3/middleware/__init__.py
chain3/middleware/abi.py
chain3/middleware/attrdict.py
chain3/middleware/cache.py
chain3/middleware/exception_handling.py
chain3/middleware/exception_retry_request.py
chain3/middleware/fixture.py
chain3/middleware/formatting.py
chain3/middleware/gas_price_strategy.py
chain3/middleware/gmc_poa.py
chain3/middleware/names.py
chain3/middleware/normalize_errors.py
chain3/middleware/pythonic.py
chain3/middleware/signing.py
chain3/middleware/simulate_unmined_transaction.py
chain3/middleware/stalecheck.py
chain3/middleware/validation.py
chain3/providers/__init__.py
chain3/providers/auto.py
chain3/providers/base.py
chain3/providers/ipc.py
chain3/providers/rpc.py
chain3/providers/tester.py
chain3/providers/websocket.py
chain3/providers/mc_tester/__init__.py
chain3/providers/mc_tester/defaults.py
chain3/providers/mc_tester/main.py
chain3/providers/mc_tester/middleware.py
chain3/utils/__init__.py
chain3/utils/abi.py
chain3/utils/blocks.py
chain3/utils/caching.py
chain3/utils/contracts.py
chain3/utils/datastructures.py
chain3/utils/datatypes.py
chain3/utils/decorators.py
chain3/utils/empty.py
chain3/utils/encoding.py
chain3/utils/ens.py
chain3/utils/events.py
chain3/utils/filters.py
chain3/utils/formatters.py
chain3/utils/function_identifiers.py
chain3/utils/http.py
chain3/utils/hypothesis.py
chain3/utils/normalizers.py
chain3/utils/request.py
chain3/utils/rpc_abi.py
chain3/utils/threads.py
chain3/utils/transactions.py
